neurobayes/__init__.py
neurobayes/__version__.py
neurobayes/flax_nets/__init__.py
neurobayes/flax_nets/config_utils.py
neurobayes/flax_nets/configs.py
neurobayes/flax_nets/convnet.py
neurobayes/flax_nets/deterministic_nn.py
neurobayes/flax_nets/ensemble.py
neurobayes/flax_nets/mlp.py
neurobayes/flax_nets/parameter_selection.py
neurobayes/flax_nets/splitter.py
neurobayes/flax_nets/train_utils.py
neurobayes/flax_nets/transformer.py
neurobayes/models/__init__.py
neurobayes/models/bnn.py
neurobayes/models/bnn_heteroskedastic.py
neurobayes/models/bnn_heteroskedastic_model.py
neurobayes/models/dkl.py
neurobayes/models/gp.py
neurobayes/models/hybrid_layers.py
neurobayes/models/kernels.py
neurobayes/models/partial_bnn.py
neurobayes/models/partial_bnn_conv.py
neurobayes/models/partial_bnn_heteroskedastic.py
neurobayes/models/partial_bnn_mlp.py
neurobayes/models/partial_bnn_transformer.py
neurobayes/models/vidkl.py
neurobayes/models/vigp.py
neurobayes/utils/__init__.py
neurobayes/utils/diagnostics.py
neurobayes/utils/genfunc.py
neurobayes/utils/priors.py
neurobayes/utils/utils.py
neurobayes-0.0.14.dist-info/METADATA
neurobayes-0.0.14.dist-info/WHEEL
neurobayes-0.0.14.dist-info/top_level.txt
neurobayes-0.0.14.dist-info/RECORD
