Metadata-Version: 2.4
Name: NeuroBayes
Version: 0.0.14
Summary: Fully and Partially Bayesian Neural Networks
Home-page: https://github.com/ziatdinovmax/NeuroBayes/
Author: Maxim Ziatdinov
Author-email: maxim.ziatdinov@gmail.com
License: MIT license
Classifier: Programming Language :: Python
Classifier: Development Status :: 3 - Alpha
Classifier: Intended Audience :: Science/Research
Classifier: Operating System :: POSIX :: Linux
Classifier: Operating System :: MacOS :: MacOS X
Classifier: Topic :: Scientific/Engineering
Requires-Python: >=3.9
Requires-Dist: jax>=0.4.0
Requires-Dist: jaxlib>=0.4.0
Requires-Dist: numpyro>=0.13.0
Requires-Dist: flax>=0.8.4
Dynamic: author
Dynamic: author-email
Dynamic: classifier
Dynamic: description
Dynamic: description-content-type
Dynamic: home-page
Dynamic: license
Dynamic: requires-dist
Dynamic: requires-python
Dynamic: summary
